[
  {
    "train_number": "12253",
    "train_name": "ANGA EXPRESS",
    "train_type": "sf",
    "source": "DKAE",
    "departure_time": "00:05",
    "destination": "BWN",
    "arrival_time": "01:04",
    "duration": "00:59H",
    "booking_available": true,
    "advance_reservation_period": "60",
    "start_date": "",
    "end_date": "",
    "booking_classes": [
      "1A",
      "2A",
      "3A",
      "SL"
    ],
    "notices": [],
    "has_pantry": true,
    "is_limited_run": false,
    "departure_datetime": "2026-06-29 09:31:04",
    "departure_datetime_str": "Unknown"
  },
  {
    "train_number": "63501",
    "train_name": "HWH BWN MEMU",
    "train_type": "pass",
    "source": "HWH",
    "departure_time": "01:45",
    "destination": "BWN",
    "arrival_time": "03:35",
    "duration": "01:50H",
    "booking_available": true,
    "advance_reservation_period": "60",
    "start_date": "",
    "end_date": "",
    "booking_classes": [],
    "notices": [],
    "has_pantry": false,
    "is_limited_run": false,
    "departure_datetime": "2026-06-29 09:31:04",
    "departure_datetime_str": "Unknown"
  },
  {
    "train_number": "13433",
    "train_name": "AMRIT BHARAT EXP",
    "train_type": "exp",
    "source": "ADL",
    "departure_time": "04:00",
    "destination": "BWN",
    "arrival_time": "06:08",
    "duration": "02:08H",
    "booking_available": true,
    "advance_reservation_period": "60",
    "start_date": "",
    "end_date": "",
    "booking_classes": [
      "SL"
    ],
    "notices": [],
    "has_pantry": false,
    "is_limited_run": false,
    "departure_datetime": "2026-06-29 09:31:04",
    "departure_datetime_str": "Unknown"
  }
]